clipkly/__init__.py
clipkly/cli.py
clipkly/core.py
clipkly/test_lib.py
clipkly/version.py
clipkly-0.1.5.dist-info/licenses/LICENSE
clipkly-0.1.5.dist-info/METADATA
clipkly-0.1.5.dist-info/WHEEL
clipkly-0.1.5.dist-info/entry_points.txt
clipkly-0.1.5.dist-info/top_level.txt
clipkly-0.1.5.dist-info/RECORD
