Metadata-Version: 2.4
Name: clipkly
Version: 0.1.5
Summary: Automatiza la creación de clips impactantes desde tus transmisiones. clipkly convierte JSONs con timecodes en cortes precisos listos para redes sociales, exportando también un Excel con metadatos editoriales. Perfecto para devs que crean, editan y publican contenido.
Home-page: https://github.com/judlup/clipkly
Author: Julian Dario Luna Patiño
Author-email: judlup@trycatch.tv
Classifier: Programming Language :: Python :: 3
Classifier: License :: OSI Approved :: MIT License
Classifier: Operating System :: OS Independent
Requires-Python: >=3.7
License-File: LICENSE
Requires-Dist: pandas
Requires-Dist: tqdm
Requires-Dist: openpyxl
Dynamic: author
Dynamic: author-email
Dynamic: classifier
Dynamic: description
Dynamic: description-content-type
Dynamic: home-page
Dynamic: license-file
Dynamic: requires-dist
Dynamic: requires-python
Dynamic: summary
